{"symbols":{"AboutComponent":{"hasNamespace":false,"type":0,"moduleName":"about.component","relativePath":"wwwroot\\app\\about.component"},"AppModule":{"hasNamespace":false,"type":0,"moduleName":"app.module","relativePath":"wwwroot\\app\\app.module"},"AppComponent":{"hasNamespace":false,"type":0,"moduleName":"app.component","relativePath":"wwwroot\\app\\app.component"},"ContactComponent":{"hasNamespace":false,"type":0,"moduleName":"contact.component","relativePath":"wwwroot\\app\\contact.component"},"LoginComponent":{"hasNamespace":false,"type":0,"moduleName":"login.component","relativePath":"wwwroot\\app\\login.component"},"IndexComponent":{"hasNamespace":false,"type":0,"moduleName":"index.component","relativePath":"wwwroot\\app\\index.component"},"RegisterComponent":{"hasNamespace":false,"type":0,"moduleName":"register.component","relativePath":"wwwroot\\app\\register.component"},"ErrorResponse":{"hasNamespace":false,"type":0,"moduleName":"ErrorResponse","relativePath":"wwwroot\\app\\models\\ErrorResponse"},"LoginViewModel":{"hasNamespace":false,"type":0,"moduleName":"LoginViewModel","relativePath":"wwwroot\\app\\models\\LoginViewModel"},"RegisterViewModel":{"hasNamespace":false,"type":0,"moduleName":"RegisterViewModel","relativePath":"wwwroot\\app\\models\\RegisterViewModel"},"ViewModelResponse":{"hasNamespace":false,"type":0,"moduleName":"ViewModelResponse","relativePath":"wwwroot\\app\\models\\ViewModelResponse"},"TestData":{"hasNamespace":false,"type":0,"moduleName":"TestData","relativePath":"wwwroot\\app\\models\\TestData"},"AuthService":{"hasNamespace":false,"type":0,"moduleName":"auth.service","relativePath":"wwwroot\\app\\security\\auth.service"},"OpenIdDictToken":{"hasNamespace":false,"type":0,"moduleName":"OpenIdDictToken","relativePath":"wwwroot\\app\\security\\OpenIdDictToken"},"AuthGuard":{"hasNamespace":false,"type":0,"moduleName":"auth-guard.service","relativePath":"wwwroot\\app\\security\\auth-guard.service"},"SampleDataService":{"hasNamespace":false,"type":0,"moduleName":"SampleData.service","relativePath":"wwwroot\\app\\services\\SampleData.service"}},"files":{"wwwroot\\app\\about.component.ts":"2017-04-26T22:05:27.799Z","wwwroot\\app\\app.module.ts":"2017-04-26T22:03:18.628Z","wwwroot\\app\\app.component.ts":"2017-04-09T21:07:01.583Z","wwwroot\\app\\app.routing.ts":"2017-03-09T19:25:52.362Z","wwwroot\\app\\contact.component.ts":"2017-04-26T22:03:03.802Z","wwwroot\\app\\login.component.ts":"2017-04-09T21:07:01.615Z","wwwroot\\app\\index.component.ts":"2017-04-05T04:04:30.435Z","wwwroot\\app\\main.ts":"2017-03-09T19:25:52.385Z","wwwroot\\app\\register.component.ts":"2017-04-05T04:04:30.462Z","wwwroot\\app\\rxjs-operators.ts":"2017-03-09T19:25:52.400Z","wwwroot\\app\\models\\ErrorResponse.ts":"2017-03-17T03:54:59.774Z","wwwroot\\app\\models\\LoginViewModel.ts":"2017-03-09T19:25:52.385Z","wwwroot\\app\\models\\RegisterViewModel.ts":"2017-03-09T19:25:52.385Z","wwwroot\\app\\models\\ViewModelResponse.ts":"2017-03-15T20:51:50.752Z","wwwroot\\app\\models\\TestData.ts":"2017-03-09T19:25:52.385Z","wwwroot\\app\\security\\auth.service.ts":"2017-04-09T21:07:01.646Z","wwwroot\\app\\security\\OpenIdDictToken.ts":"2017-03-09T19:25:52.400Z","wwwroot\\app\\security\\auth-guard.service.ts":"2017-04-05T04:04:30.477Z","wwwroot\\app\\services\\SampleData.service.ts":"2017-03-15T20:51:50.758Z"}}